<Spawns>
  <Points>
    <Name>Grassland 01</Name>
    <UniqueId>14bfbec9-ffb8-4181-a635-29ff57049336</UniqueId>
    <Map>Tykari</Map>
    <X>2812</X>
    <Y>1320</Y>
    <Width>248</Width>
    <Height>88</Height>
    <CentreX>2936</CentreX>
    <CentreY>1364</CentreY>
    <CentreZ>-32768</CentreZ>
    <Range>60</Range>
    <MaxCount>60</MaxCount>
    <MinDelay>480</MinDelay>
    <MaxDelay>720</MaxDelay>
    <Team>0</Team>
    <IsGroup>False</IsGroup>
    <IsRunning>True</IsRunning>
    <IsHomeRangeRelative>True</IsHomeRangeRelative>
    <DelayInSec>True</DelayInSec>
    <Duration>0</Duration>
    <DespawnTime>0</DespawnTime>
    <ProximityRange>-1</ProximityRange>
    <ProximityTriggerSound>500</ProximityTriggerSound>
    <TriggerProbability>1</TriggerProbability>
    <InContainer>False</InContainer>
    <MinRefractory>0</MinRefractory>
    <MaxRefractory>0</MaxRefractory>
    <TODStart>0</TODStart>
    <TODEnd>0</TODEnd>
    <TODMode>0</TODMode>
    <KillReset>1</KillReset>
    <ExternalTriggering>False</ExternalTriggering>
    <SequentialSpawning>-1</SequentialSpawning>
    <AllowGhostTriggering>False</AllowGhostTriggering>
    <SpawnOnTrigger>False</SpawnOnTrigger>
    <SmartSpawning>False</SmartSpawning>
    <Amount>1</Amount>
    <Objects2>Wraith:MX=12:SB=0:RT=0:TO=0:KL=0:RK=0:CA=1:DN=-1:DX=-1:SP=1:OBJ=Ratman:MX=10:SB=0:RT=0:TO=0:KL=0:RK=0:CA=1:DN=-1:DX=-1:SP=1:OBJ=AirElemental:MX=6:SB=0:RT=0:TO=0:KL=0:RK=0:CA=1:DN=-1:DX=-1:SP=1:OBJ=Brigand:MX=4:SB=0:RT=0:TO=0:KL=0:RK=0:CA=1:DN=-1:DX=-1:SP=1:OBJ=Harpy:MX=10:SB=0:RT=0:TO=0:KL=0:RK=0:CA=1:DN=-1:DX=-1:SP=1:OBJ=Orc:MX=10:SB=0:RT=0:TO=0:KL=0:RK=0:CA=1:DN=-1:DX=-1:SP=1:OBJ=OrcishLord:MX=8:SB=0:RT=0:TO=0:KL=0:RK=0:CA=1:DN=-1:DX=-1:SP=1</Objects2>
  </Points>
  <Points>
    <Name>Grassland 02</Name>
    <UniqueId>c5561c83-a6fd-4871-9bd1-d1ac67aeca51</UniqueId>
    <Map>Tykari</Map>
    <X>3168</X>
    <Y>1504</Y>
    <Width>120</Width>
    <Height>188</Height>
    <CentreX>3228</CentreX>
    <CentreY>1598</CentreY>
    <CentreZ>-32768</CentreZ>
    <Range>65</Range>
    <MaxCount>51</MaxCount>
    <MinDelay>360</MinDelay>
    <MaxDelay>840</MaxDelay>
    <Team>0</Team>
    <IsGroup>False</IsGroup>
    <IsRunning>True</IsRunning>
    <IsHomeRangeRelative>True</IsHomeRangeRelative>
    <DelayInSec>True</DelayInSec>
    <Duration>0</Duration>
    <DespawnTime>0</DespawnTime>
    <ProximityRange>-1</ProximityRange>
    <ProximityTriggerSound>500</ProximityTriggerSound>
    <TriggerProbability>1</TriggerProbability>
    <InContainer>False</InContainer>
    <MinRefractory>0</MinRefractory>
    <MaxRefractory>0</MaxRefractory>
    <TODStart>0</TODStart>
    <TODEnd>0</TODEnd>
    <TODMode>0</TODMode>
    <KillReset>1</KillReset>
    <ExternalTriggering>False</ExternalTriggering>
    <SequentialSpawning>-1</SequentialSpawning>
    <AllowGhostTriggering>False</AllowGhostTriggering>
    <SpawnOnTrigger>False</SpawnOnTrigger>
    <SmartSpawning>False</SmartSpawning>
    <Amount>1</Amount>
    <Objects2>Harpy:MX=4:SB=0:RT=0:TO=0:KL=0:RK=0:CA=1:DN=-1:DX=-1:SP=1:OBJ=Ratman:MX=8:SB=0:RT=0:TO=0:KL=0:RK=0:CA=1:DN=-1:DX=-1:SP=1:OBJ=RatmanMage:MX=5:SB=0:RT=0:TO=0:KL=0:RK=0:CA=1:DN=-1:DX=-1:SP=1:OBJ=RatmanArcher:MX=5:SB=0:RT=0:TO=0:KL=0:RK=0:CA=1:DN=-1:DX=-1:SP=1:OBJ=Ogre:MX=4:SB=0:RT=0:TO=0:KL=0:RK=0:CA=1:DN=-1:DX=-1:SP=1:OBJ=OgreLord:MX=2:SB=0:RT=0:TO=0:KL=0:RK=0:CA=1:DN=-1:DX=-1:SP=1:OBJ=Wisp:MX=2:SB=0:RT=0:TO=0:KL=0:RK=0:CA=1:DN=-1:DX=-1:SP=1:OBJ=AirElemental:MX=4:SB=0:RT=0:TO=0:KL=0:RK=0:CA=1:DN=-1:DX=-1:SP=1:OBJ=Cyclops:MX=1:SB=0:RT=0:TO=0:KL=0:RK=0:CA=1:DN=-1:DX=-1:SP=1:OBJ=Mongbat:MX=8:SB=0:RT=0:TO=0:KL=0:RK=0:CA=1:DN=-1:DX=-1:SP=1:OBJ=Ghoul:MX=8:SB=0:RT=0:TO=0:KL=0:RK=0:CA=1:DN=-1:DX=-1:SP=1</Objects2>
  </Points>
  <Points>
    <Name>Grassland 03</Name>
    <UniqueId>a7ade31d-ba8b-48fd-9ec7-c1171d4d3b80</UniqueId>
    <Map>Tykari</Map>
    <X>3928</X>
    <Y>1428</Y>
    <Width>192</Width>
    <Height>120</Height>
    <CentreX>4024</CentreX>
    <CentreY>1488</CentreY>
    <CentreZ>-32768</CentreZ>
    <Range>60</Range>
    <MaxCount>43</MaxCount>
    <MinDelay>360</MinDelay>
    <MaxDelay>840</MaxDelay>
    <Team>0</Team>
    <IsGroup>False</IsGroup>
    <IsRunning>True</IsRunning>
    <IsHomeRangeRelative>True</IsHomeRangeRelative>
    <DelayInSec>True</DelayInSec>
    <Duration>0</Duration>
    <DespawnTime>0</DespawnTime>
    <ProximityRange>-1</ProximityRange>
    <ProximityTriggerSound>500</ProximityTriggerSound>
    <TriggerProbability>1</TriggerProbability>
    <InContainer>False</InContainer>
    <MinRefractory>0</MinRefractory>
    <MaxRefractory>0</MaxRefractory>
    <TODStart>0</TODStart>
    <TODEnd>0</TODEnd>
    <TODMode>0</TODMode>
    <KillReset>1</KillReset>
    <ExternalTriggering>False</ExternalTriggering>
    <SequentialSpawning>-1</SequentialSpawning>
    <AllowGhostTriggering>False</AllowGhostTriggering>
    <SpawnOnTrigger>False</SpawnOnTrigger>
    <SmartSpawning>False</SmartSpawning>
    <Amount>1</Amount>
    <Objects2>Ettin:MX=3:SB=0:RT=0:TO=0:KL=0:RK=0:CA=1:DN=-1:DX=-1:SP=1:OBJ=Orc:MX=5:SB=0:RT=0:TO=0:KL=0:RK=0:CA=1:DN=-1:DX=-1:SP=1:OBJ=OrcCaptain:MX=3:SB=0:RT=0:TO=0:KL=0:RK=0:CA=1:DN=-1:DX=-1:SP=1:OBJ=StoneHarpy:MX=3:SB=0:RT=0:TO=0:KL=0:RK=0:CA=1:DN=-1:DX=-1:SP=1:OBJ=Gazer:MX=2:SB=0:RT=0:TO=0:KL=0:RK=0:CA=1:DN=-1:DX=-1:SP=1:OBJ=Mongbat:MX=6:SB=0:RT=0:TO=0:KL=0:RK=0:CA=1:DN=-1:DX=-1:SP=1:OBJ=Troll:MX=3:SB=0:RT=0:TO=0:KL=0:RK=0:CA=1:DN=-1:DX=-1:SP=1:OBJ=SkeletalKnight:MX=3:SB=0:RT=0:TO=0:KL=0:RK=0:CA=1:DN=-1:DX=-1:SP=1:OBJ=Skeleton:MX=5:SB=0:RT=0:TO=0:KL=0:RK=0:CA=1:DN=-1:DX=-1:SP=1:OBJ=Spectre:MX=4:SB=0:RT=0:TO=0:KL=0:RK=0:CA=1:DN=-1:DX=-1:SP=1:OBJ=Shade:MX=6:SB=0:RT=0:TO=0:KL=0:RK=0:CA=1:DN=-1:DX=-1:SP=1</Objects2>
  </Points>
  <Points>
    <Name>Grassland 04</Name>
    <UniqueId>5da0c0cc-f66d-44cf-8a59-3e3d4021c7b3</UniqueId>
    <Map>Tykari</Map>
    <X>4148</X>
    <Y>1188</Y>
    <Width>464</Width>
    <Height>80</Height>
    <CentreX>4380</CentreX>
    <CentreY>1228</CentreY>
    <CentreZ>-32768</CentreZ>
    <Range>40</Range>
    <MaxCount>43</MaxCount>
    <MinDelay>300</MinDelay>
    <MaxDelay>600</MaxDelay>
    <Team>0</Team>
    <IsGroup>False</IsGroup>
    <IsRunning>True</IsRunning>
    <IsHomeRangeRelative>True</IsHomeRangeRelative>
    <DelayInSec>True</DelayInSec>
    <Duration>0</Duration>
    <DespawnTime>0</DespawnTime>
    <ProximityRange>-1</ProximityRange>
    <ProximityTriggerSound>500</ProximityTriggerSound>
    <TriggerProbability>1</TriggerProbability>
    <InContainer>False</InContainer>
    <MinRefractory>0</MinRefractory>
    <MaxRefractory>0</MaxRefractory>
    <TODStart>0</TODStart>
    <TODEnd>0</TODEnd>
    <TODMode>0</TODMode>
    <KillReset>1</KillReset>
    <ExternalTriggering>False</ExternalTriggering>
    <SequentialSpawning>-1</SequentialSpawning>
    <AllowGhostTriggering>False</AllowGhostTriggering>
    <SpawnOnTrigger>False</SpawnOnTrigger>
    <SmartSpawning>False</SmartSpawning>
    <Amount>1</Amount>
    <Objects2>Cyclops:MX=4:SB=0:RT=0:TO=0:KL=0:RK=0:CA=1:DN=-1:DX=-1:SP=1:OBJ=Titan:MX=3:SB=0:RT=0:TO=0:KL=0:RK=0:CA=1:DN=-1:DX=-1:SP=1:OBJ=Mongbat:MX=6:SB=0:RT=0:TO=0:KL=0:RK=0:CA=1:DN=-1:DX=-1:SP=1:OBJ=Ettin:MX=6:SB=0:RT=0:TO=0:KL=0:RK=0:CA=1:DN=-1:DX=-1:SP=1:OBJ=Troll:MX=5:SB=0:RT=0:TO=0:KL=0:RK=0:CA=1:DN=-1:DX=-1:SP=1:OBJ=HeadlessOne:MX=8:SB=0:RT=0:TO=0:KL=0:RK=0:CA=1:DN=-1:DX=-1:SP=1:OBJ=Wraith:MX=5:SB=0:RT=0:TO=0:KL=0:RK=0:CA=1:DN=-1:DX=-1:SP=1:OBJ=StoneGargoyle:MX=6:SB=0:RT=0:TO=0:KL=0:RK=0:CA=1:DN=-1:DX=-1:SP=1</Objects2>
  </Points>
  <Points>
    <Name>Grassland 05</Name>
    <UniqueId>fbe3d792-1fcc-44a2-bb9c-26daa4ee027e</UniqueId>
    <Map>Tykari</Map>
    <X>4580</X>
    <Y>1276</Y>
    <Width>340</Width>
    <Height>268</Height>
    <CentreX>4750</CentreX>
    <CentreY>1410</CentreY>
    <CentreZ>-32768</CentreZ>
    <Range>30</Range>
    <MaxCount>39</MaxCount>
    <MinDelay>300</MinDelay>
    <MaxDelay>600</MaxDelay>
    <Team>0</Team>
    <IsGroup>False</IsGroup>
    <IsRunning>True</IsRunning>
    <IsHomeRangeRelative>True</IsHomeRangeRelative>
    <DelayInSec>True</DelayInSec>
    <Duration>0</Duration>
    <DespawnTime>0</DespawnTime>
    <ProximityRange>-1</ProximityRange>
    <ProximityTriggerSound>500</ProximityTriggerSound>
    <TriggerProbability>1</TriggerProbability>
    <InContainer>False</InContainer>
    <MinRefractory>0</MinRefractory>
    <MaxRefractory>0</MaxRefractory>
    <TODStart>0</TODStart>
    <TODEnd>0</TODEnd>
    <TODMode>0</TODMode>
    <KillReset>1</KillReset>
    <ExternalTriggering>False</ExternalTriggering>
    <SequentialSpawning>-1</SequentialSpawning>
    <AllowGhostTriggering>False</AllowGhostTriggering>
    <SpawnOnTrigger>False</SpawnOnTrigger>
    <SmartSpawning>False</SmartSpawning>
    <Amount>1</Amount>
    <Objects2>Cyclops:MX=4:SB=0:RT=0:TO=0:KL=0:RK=0:CA=1:DN=-1:DX=-1:SP=1:OBJ=Titan:MX=2:SB=0:RT=0:TO=0:KL=0:RK=0:CA=1:DN=-1:DX=-1:SP=1:OBJ=StoneHarpy:MX=4:SB=0:RT=0:TO=0:KL=0:RK=0:CA=1:DN=-1:DX=-1:SP=1:OBJ=StoneGargoyle:MX=3:SB=0:RT=0:TO=0:KL=0:RK=0:CA=1:DN=-1:DX=-1:SP=1:OBJ=ElderGazer:MX=2:SB=0:RT=0:TO=0:KL=0:RK=0:CA=1:DN=-1:DX=-1:SP=1:OBJ=Gazer:MX=3:SB=0:RT=0:TO=0:KL=0:RK=0:CA=1:DN=-1:DX=-1:SP=1:OBJ=Gargoyle:MX=4:SB=0:RT=0:TO=0:KL=0:RK=0:CA=1:DN=-1:DX=-1:SP=1:OBJ=AirElemental:MX=4:SB=0:RT=0:TO=0:KL=0:RK=0:CA=1:DN=-1:DX=-1:SP=1:OBJ=Ogre:MX=5:SB=0:RT=0:TO=0:KL=0:RK=0:CA=1:DN=-1:DX=-1:SP=1:OBJ=OgreLord:MX=3:SB=0:RT=0:TO=0:KL=0:RK=0:CA=1:DN=-1:DX=-1:SP=1:OBJ=Troll:MX=5:SB=0:RT=0:TO=0:KL=0:RK=0:CA=1:DN=-1:DX=-1:SP=1</Objects2>
  </Points>
  <Points>
    <Name>Grassland 06</Name>
    <UniqueId>5971ee2d-efa3-4d65-8662-08c787b1dce7</UniqueId>
    <Map>Tykari</Map>
    <X>4272</X>
    <Y>1308</Y>
    <Width>260</Width>
    <Height>176</Height>
    <CentreX>4402</CentreX>
    <CentreY>1396</CentreY>
    <CentreZ>-32768</CentreZ>
    <Range>50</Range>
    <MaxCount>50</MaxCount>
    <MinDelay>240</MinDelay>
    <MaxDelay>720</MaxDelay>
    <Team>0</Team>
    <IsGroup>False</IsGroup>
    <IsRunning>True</IsRunning>
    <IsHomeRangeRelative>True</IsHomeRangeRelative>
    <DelayInSec>True</DelayInSec>
    <Duration>0</Duration>
    <DespawnTime>0</DespawnTime>
    <ProximityRange>-1</ProximityRange>
    <ProximityTriggerSound>500</ProximityTriggerSound>
    <TriggerProbability>1</TriggerProbability>
    <InContainer>False</InContainer>
    <MinRefractory>0</MinRefractory>
    <MaxRefractory>0</MaxRefractory>
    <TODStart>0</TODStart>
    <TODEnd>0</TODEnd>
    <TODMode>0</TODMode>
    <KillReset>1</KillReset>
    <ExternalTriggering>False</ExternalTriggering>
    <SequentialSpawning>-1</SequentialSpawning>
    <AllowGhostTriggering>False</AllowGhostTriggering>
    <SpawnOnTrigger>False</SpawnOnTrigger>
    <SmartSpawning>False</SmartSpawning>
    <Amount>1</Amount>
    <Objects2>Reaper:MX=3:SB=0:RT=0:TO=0:KL=0:RK=0:CA=1:DN=-1:DX=-1:SP=1:OBJ=Ghoul:MX=6:SB=0:RT=0:TO=0:KL=0:RK=0:CA=1:DN=-1:DX=-1:SP=1:OBJ=Skeleton:MX=8:SB=0:RT=0:TO=0:KL=0:RK=0:CA=1:DN=-1:DX=-1:SP=1:OBJ=Ratman:MX=6:SB=0:RT=0:TO=0:KL=0:RK=0:CA=1:DN=-1:DX=-1:SP=1:OBJ=RatmanArcher:MX=4:SB=0:RT=0:TO=0:KL=0:RK=0:CA=1:DN=-1:DX=-1:SP=1:OBJ=Mongbat:MX=5:SB=0:RT=0:TO=0:KL=0:RK=0:CA=1:DN=-1:DX=-1:SP=1:OBJ=Orc:MX=5:SB=0:RT=0:TO=0:KL=0:RK=0:CA=1:DN=-1:DX=-1:SP=1:OBJ=OrcishLord:MX=4:SB=0:RT=0:TO=0:KL=0:RK=0:CA=1:DN=-1:DX=-1:SP=1:OBJ=OrcishMage:MX=3:SB=0:RT=0:TO=0:KL=0:RK=0:CA=1:DN=-1:DX=-1:SP=1:OBJ=Brigand/Team/1:MX=6:SB=0:RT=0:TO=0:KL=0:RK=0:CA=1:DN=-1:DX=-1:SP=1</Objects2>
  </Points>
  <Points>
    <Name>Grassland 07</Name>
    <UniqueId>22695f3c-5683-4807-930b-7bebcec656df</UniqueId>
    <Map>Tykari</Map>
    <X>4084</X>
    <Y>1628</Y>
    <Width>104</Width>
    <Height>308</Height>
    <CentreX>4136</CentreX>
    <CentreY>1782</CentreY>
    <CentreZ>-32768</CentreZ>
    <Range>40</Range>
    <MaxCount>38</MaxCount>
    <MinDelay>300</MinDelay>
    <MaxDelay>900</MaxDelay>
    <Team>0</Team>
    <IsGroup>False</IsGroup>
    <IsRunning>True</IsRunning>
    <IsHomeRangeRelative>True</IsHomeRangeRelative>
    <DelayInSec>True</DelayInSec>
    <Duration>0</Duration>
    <DespawnTime>0</DespawnTime>
    <ProximityRange>-1</ProximityRange>
    <ProximityTriggerSound>500</ProximityTriggerSound>
    <TriggerProbability>1</TriggerProbability>
    <InContainer>False</InContainer>
    <MinRefractory>0</MinRefractory>
    <MaxRefractory>0</MaxRefractory>
    <TODStart>0</TODStart>
    <TODEnd>0</TODEnd>
    <TODMode>0</TODMode>
    <KillReset>1</KillReset>
    <ExternalTriggering>False</ExternalTriggering>
    <SequentialSpawning>-1</SequentialSpawning>
    <AllowGhostTriggering>False</AllowGhostTriggering>
    <SpawnOnTrigger>False</SpawnOnTrigger>
    <SmartSpawning>False</SmartSpawning>
    <Amount>1</Amount>
    <Objects2>Mongbat:MX=8:SB=0:RT=0:TO=0:KL=0:RK=0:CA=1:DN=-1:DX=-1:SP=1:OBJ=Bogle:MX=6:SB=0:RT=0:TO=0:KL=0:RK=0:CA=1:DN=-1:DX=-1:SP=1:OBJ=Wisp/Team/1:MX=2:SB=0:RT=0:TO=0:KL=0:RK=0:CA=1:DN=-1:DX=-1:SP=1:OBJ=Brigand/Team/2:MX=5:SB=0:RT=0:TO=0:KL=0:RK=0:CA=1:DN=-1:DX=-1:SP=1:OBJ=Skeleton:MX=6:SB=0:RT=0:TO=0:KL=0:RK=0:CA=1:DN=-1:DX=-1:SP=1:OBJ=SkeletalKnight:MX=4:SB=0:RT=0:TO=0:KL=0:RK=0:CA=1:DN=-1:DX=-1:SP=1:OBJ=Wraith:MX=4:SB=0:RT=0:TO=0:KL=0:RK=0:CA=1:DN=-1:DX=-1:SP=1:OBJ=Gazer:MX=3:SB=0:RT=0:TO=0:KL=0:RK=0:CA=1:DN=-1:DX=-1:SP=1</Objects2>
  </Points>
  <Points>
    <Name>Grassland 08</Name>
    <UniqueId>492ec666-1eb1-404c-a012-e437bb54b3c7</UniqueId>
    <Map>Tykari</Map>
    <X>4372</X>
    <Y>1568</Y>
    <Width>540</Width>
    <Height>336</Height>
    <CentreX>4642</CentreX>
    <CentreY>1736</CentreY>
    <CentreZ>-32768</CentreZ>
    <Range>45</Range>
    <MaxCount>97</MaxCount>
    <MinDelay>240</MinDelay>
    <MaxDelay>480</MaxDelay>
    <Team>0</Team>
    <IsGroup>False</IsGroup>
    <IsRunning>True</IsRunning>
    <IsHomeRangeRelative>True</IsHomeRangeRelative>
    <DelayInSec>True</DelayInSec>
    <Duration>0</Duration>
    <DespawnTime>0</DespawnTime>
    <ProximityRange>-1</ProximityRange>
    <ProximityTriggerSound>500</ProximityTriggerSound>
    <TriggerProbability>1</TriggerProbability>
    <InContainer>False</InContainer>
    <MinRefractory>0</MinRefractory>
    <MaxRefractory>0</MaxRefractory>
    <TODStart>0</TODStart>
    <TODEnd>0</TODEnd>
    <TODMode>0</TODMode>
    <KillReset>1</KillReset>
    <ExternalTriggering>False</ExternalTriggering>
    <SequentialSpawning>-1</SequentialSpawning>
    <AllowGhostTriggering>False</AllowGhostTriggering>
    <SpawnOnTrigger>False</SpawnOnTrigger>
    <SmartSpawning>False</SmartSpawning>
    <Amount>1</Amount>
    <Objects2>Orc:MX=8:SB=0:RT=0:TO=0:KL=0:RK=0:CA=1:DN=-1:DX=-1:SP=1:OBJ=OrcishMage:MX=3:SB=0:RT=0:TO=0:KL=0:RK=0:CA=1:DN=-1:DX=-1:SP=1:OBJ=OrcishLord:MX=3:SB=0:RT=0:TO=0:KL=0:RK=0:CA=1:DN=-1:DX=-1:SP=1:OBJ=OrcCaptain:MX=4:SB=0:RT=0:TO=0:KL=0:RK=0:CA=1:DN=-1:DX=-1:SP=1:OBJ=Ratman:MX=6:SB=0:RT=0:TO=0:KL=0:RK=0:CA=1:DN=-1:DX=-1:SP=1:OBJ=RatmanArcher:MX=5:SB=0:RT=0:TO=0:KL=0:RK=0:CA=1:DN=-1:DX=-1:SP=1:OBJ=Gazer:MX=4:SB=0:RT=0:TO=0:KL=0:RK=0:CA=1:DN=-1:DX=-1:SP=1:OBJ=Reaper:MX=4:SB=0:RT=0:TO=0:KL=0:RK=0:CA=1:DN=-1:DX=-1:SP=1:OBJ=Spectre:MX=6:SB=0:RT=0:TO=0:KL=0:RK=0:CA=1:DN=-1:DX=-1:SP=1:OBJ=Ettin:MX=10:SB=0:RT=0:TO=0:KL=0:RK=0:CA=1:DN=-1:DX=-1:SP=1:OBJ=Ogre:MX=10:SB=0:RT=0:TO=0:KL=0:RK=0:CA=1:DN=-1:DX=-1:SP=1:OBJ=HeadlessOne:MX=8:SB=0:RT=0:TO=0:KL=0:RK=0:CA=1:DN=-1:DX=-1:SP=1:OBJ=AirElemental:MX=8:SB=0:RT=0:TO=0:KL=0:RK=0:CA=1:DN=-1:DX=-1:SP=1:OBJ=Skeleton:MX=12:SB=0:RT=0:TO=0:KL=0:RK=0:CA=1:DN=-1:DX=-1:SP=1:OBJ=BoneKnight:MX=6:SB=0:RT=0:TO=0:KL=0:RK=0:CA=1:DN=-1:DX=-1:SP=1</Objects2>
  </Points>
  <Points>
    <Name>Grassland 09</Name>
    <UniqueId>8469732f-4593-4061-9aca-c665552137ba</UniqueId>
    <Map>Tykari</Map>
    <X>2572</X>
    <Y>2324</Y>
    <Width>168</Width>
    <Height>116</Height>
    <CentreX>2656</CentreX>
    <CentreY>2382</CentreY>
    <CentreZ>-32768</CentreZ>
    <Range>45</Range>
    <MaxCount>40</MaxCount>
    <MinDelay>240</MinDelay>
    <MaxDelay>720</MaxDelay>
    <Team>0</Team>
    <IsGroup>False</IsGroup>
    <IsRunning>True</IsRunning>
    <IsHomeRangeRelative>True</IsHomeRangeRelative>
    <DelayInSec>True</DelayInSec>
    <Duration>0</Duration>
    <DespawnTime>0</DespawnTime>
    <ProximityRange>-1</ProximityRange>
    <ProximityTriggerSound>500</ProximityTriggerSound>
    <TriggerProbability>1</TriggerProbability>
    <InContainer>False</InContainer>
    <MinRefractory>0</MinRefractory>
    <MaxRefractory>0</MaxRefractory>
    <TODStart>0</TODStart>
    <TODEnd>0</TODEnd>
    <TODMode>0</TODMode>
    <KillReset>1</KillReset>
    <ExternalTriggering>False</ExternalTriggering>
    <SequentialSpawning>-1</SequentialSpawning>
    <AllowGhostTriggering>False</AllowGhostTriggering>
    <SpawnOnTrigger>False</SpawnOnTrigger>
    <SmartSpawning>False</SmartSpawning>
    <Amount>1</Amount>
    <Objects2>Troll:MX=6:SB=0:RT=0:TO=0:KL=0:RK=0:CA=1:DN=-1:DX=-1:SP=1:OBJ=Ogre:MX=5:SB=0:RT=0:TO=0:KL=0:RK=0:CA=1:DN=-1:DX=-1:SP=1:OBJ=Harpy:MX=6:SB=0:RT=0:TO=0:KL=0:RK=0:CA=1:DN=-1:DX=-1:SP=1:OBJ=Ratman:MX=8:SB=0:RT=0:TO=0:KL=0:RK=0:CA=1:DN=-1:DX=-1:SP=1:OBJ=RatmanMage:MX=5:SB=0:RT=0:TO=0:KL=0:RK=0:CA=1:DN=-1:DX=-1:SP=1:OBJ=Ghoul:MX=6:SB=0:RT=0:TO=0:KL=0:RK=0:CA=1:DN=-1:DX=-1:SP=1:OBJ=Brigand/Team/2:MX=4:SB=0:RT=0:TO=0:KL=0:RK=0:CA=1:DN=-1:DX=-1:SP=1</Objects2>
  </Points>
  <Points>
    <Name>Grassland 10</Name>
    <UniqueId>ac3c7f20-3453-4b73-b350-fe2164221231</UniqueId>
    <Map>Tykari</Map>
    <X>2224</X>
    <Y>2500</Y>
    <Width>488</Width>
    <Height>88</Height>
    <CentreX>2468</CentreX>
    <CentreY>2544</CentreY>
    <CentreZ>-32768</CentreZ>
    <Range>40</Range>
    <MaxCount>37</MaxCount>
    <MinDelay>360</MinDelay>
    <MaxDelay>720</MaxDelay>
    <Team>0</Team>
    <IsGroup>False</IsGroup>
    <IsRunning>True</IsRunning>
    <IsHomeRangeRelative>True</IsHomeRangeRelative>
    <DelayInSec>True</DelayInSec>
    <Duration>0</Duration>
    <DespawnTime>0</DespawnTime>
    <ProximityRange>-1</ProximityRange>
    <ProximityTriggerSound>500</ProximityTriggerSound>
    <TriggerProbability>1</TriggerProbability>
    <InContainer>False</InContainer>
    <MinRefractory>0</MinRefractory>
    <MaxRefractory>0</MaxRefractory>
    <TODStart>0</TODStart>
    <TODEnd>0</TODEnd>
    <TODMode>0</TODMode>
    <KillReset>1</KillReset>
    <ExternalTriggering>False</ExternalTriggering>
    <SequentialSpawning>-1</SequentialSpawning>
    <AllowGhostTriggering>False</AllowGhostTriggering>
    <SpawnOnTrigger>False</SpawnOnTrigger>
    <SmartSpawning>False</SmartSpawning>
    <Amount>1</Amount>
    <Objects2>Cyclops:MX=5:SB=0:RT=0:TO=0:KL=0:RK=0:CA=1:DN=-1:DX=-1:SP=1:OBJ=Titan:MX=3:SB=0:RT=0:TO=0:KL=0:RK=0:CA=1:DN=-1:DX=-1:SP=1:OBJ=Drake:MX=2:SB=0:RT=0:TO=0:KL=0:RK=0:CA=1:DN=-1:DX=-1:SP=1:OBJ=Ettin:MX=5:SB=0:RT=0:TO=0:KL=0:RK=0:CA=1:DN=-1:DX=-1:SP=1:OBJ=Troll:MX=4:SB=0:RT=0:TO=0:KL=0:RK=0:CA=1:DN=-1:DX=-1:SP=1:OBJ=Orc:MX=8:SB=0:RT=0:TO=0:KL=0:RK=0:CA=1:DN=-1:DX=-1:SP=1:OBJ=Mongbat:MX=6:SB=0:RT=0:TO=0:KL=0:RK=0:CA=1:DN=-1:DX=-1:SP=1:OBJ=Harpy:MX=4:SB=0:RT=0:TO=0:KL=0:RK=0:CA=1:DN=-1:DX=-1:SP=1</Objects2>
  </Points>
  <Points>
    <Name>Grassland 11</Name>
    <UniqueId>cb2855b7-173c-45a6-a9b8-98bf8e2b0c7d</UniqueId>
    <Map>Tykari</Map>
    <X>1876</X>
    <Y>2608</Y>
    <Width>468</Width>
    <Height>112</Height>
    <CentreX>2110</CentreX>
    <CentreY>2664</CentreY>
    <CentreZ>-32768</CentreZ>
    <Range>35</Range>
    <MaxCount>37</MaxCount>
    <MinDelay>240</MinDelay>
    <MaxDelay>480</MaxDelay>
    <Team>0</Team>
    <IsGroup>False</IsGroup>
    <IsRunning>True</IsRunning>
    <IsHomeRangeRelative>True</IsHomeRangeRelative>
    <DelayInSec>True</DelayInSec>
    <Duration>0</Duration>
    <DespawnTime>0</DespawnTime>
    <ProximityRange>-1</ProximityRange>
    <ProximityTriggerSound>500</ProximityTriggerSound>
    <TriggerProbability>1</TriggerProbability>
    <InContainer>False</InContainer>
    <MinRefractory>0</MinRefractory>
    <MaxRefractory>0</MaxRefractory>
    <TODStart>0</TODStart>
    <TODEnd>0</TODEnd>
    <TODMode>0</TODMode>
    <KillReset>1</KillReset>
    <ExternalTriggering>False</ExternalTriggering>
    <SequentialSpawning>-1</SequentialSpawning>
    <AllowGhostTriggering>False</AllowGhostTriggering>
    <SpawnOnTrigger>False</SpawnOnTrigger>
    <SmartSpawning>False</SmartSpawning>
    <Amount>1</Amount>
    <Objects2>Gargoyle:MX=4:SB=0:RT=0:TO=0:KL=0:RK=0:CA=1:DN=-1:DX=-1:SP=1:OBJ=Wraith:MX=5:SB=0:RT=0:TO=0:KL=0:RK=0:CA=1:DN=-1:DX=-1:SP=1:OBJ=Gazer:MX=4:SB=0:RT=0:TO=0:KL=0:RK=0:CA=1:DN=-1:DX=-1:SP=1:OBJ=Mongbat:MX=8:SB=0:RT=0:TO=0:KL=0:RK=0:CA=1:DN=-1:DX=-1:SP=1:OBJ=OrcishLord:MX=4:SB=0:RT=0:TO=0:KL=0:RK=0:CA=1:DN=-1:DX=-1:SP=1:OBJ=HeadlessOne:MX=6:SB=0:RT=0:TO=0:KL=0:RK=0:CA=1:DN=-1:DX=-1:SP=1:OBJ=Troll:MX=6:SB=0:RT=0:TO=0:KL=0:RK=0:CA=1:DN=-1:DX=-1:SP=1</Objects2>
  </Points>
  <Points>
    <Name>Grassland 12</Name>
    <UniqueId>a17004a9-ab4c-4ce1-acd2-dccc41a25429</UniqueId>
    <Map>Tykari</Map>
    <X>1448</X>
    <Y>2392</Y>
    <Width>308</Width>
    <Height>152</Height>
    <CentreX>1602</CentreX>
    <CentreY>2468</CentreY>
    <CentreZ>-32768</CentreZ>
    <Range>35</Range>
    <MaxCount>34</MaxCount>
    <MinDelay>300</MinDelay>
    <MaxDelay>900</MaxDelay>
    <Team>0</Team>
    <IsGroup>False</IsGroup>
    <IsRunning>True</IsRunning>
    <IsHomeRangeRelative>True</IsHomeRangeRelative>
    <DelayInSec>True</DelayInSec>
    <Duration>0</Duration>
    <DespawnTime>0</DespawnTime>
    <ProximityRange>-1</ProximityRange>
    <ProximityTriggerSound>500</ProximityTriggerSound>
    <TriggerProbability>1</TriggerProbability>
    <InContainer>False</InContainer>
    <MinRefractory>0</MinRefractory>
    <MaxRefractory>0</MaxRefractory>
    <TODStart>0</TODStart>
    <TODEnd>0</TODEnd>
    <TODMode>0</TODMode>
    <KillReset>1</KillReset>
    <ExternalTriggering>False</ExternalTriggering>
    <SequentialSpawning>-1</SequentialSpawning>
    <AllowGhostTriggering>False</AllowGhostTriggering>
    <SpawnOnTrigger>False</SpawnOnTrigger>
    <SmartSpawning>False</SmartSpawning>
    <Amount>1</Amount>
    <Objects2>Cyclops:MX=4:SB=0:RT=0:TO=0:KL=0:RK=0:CA=1:DN=-1:DX=-1:SP=1:OBJ=Ettin:MX=4:SB=0:RT=0:TO=0:KL=0:RK=0:CA=1:DN=-1:DX=-1:SP=1:OBJ=Troll:MX=6:SB=0:RT=0:TO=0:KL=0:RK=0:CA=1:DN=-1:DX=-1:SP=1:OBJ=Harpy:MX=5:SB=0:RT=0:TO=0:KL=0:RK=0:CA=1:DN=-1:DX=-1:SP=1:OBJ=StoneHarpy:MX=4:SB=0:RT=0:TO=0:KL=0:RK=0:CA=1:DN=-1:DX=-1:SP=1:OBJ=Ratman:MX=6:SB=0:RT=0:TO=0:KL=0:RK=0:CA=1:DN=-1:DX=-1:SP=1:OBJ=RatmanArcher:MX=3:SB=0:RT=0:TO=0:KL=0:RK=0:CA=1:DN=-1:DX=-1:SP=1:OBJ=RatmanMage:MX=2:SB=0:RT=0:TO=0:KL=0:RK=0:CA=1:DN=-1:DX=-1:SP=1</Objects2>
  </Points>
  <Points>
    <Name>Grassland 13</Name>
    <UniqueId>4348c151-9666-48a7-8c22-c13345901b28</UniqueId>
    <Map>Tykari</Map>
    <X>1776</X>
    <Y>2508</Y>
    <Width>440</Width>
    <Height>100</Height>
    <CentreX>1996</CentreX>
    <CentreY>2558</CentreY>
    <CentreZ>-32768</CentreZ>
    <Range>35</Range>
    <MaxCount>38</MaxCount>
    <MinDelay>300</MinDelay>
    <MaxDelay>600</MaxDelay>
    <Team>0</Team>
    <IsGroup>False</IsGroup>
    <IsRunning>True</IsRunning>
    <IsHomeRangeRelative>True</IsHomeRangeRelative>
    <DelayInSec>True</DelayInSec>
    <Duration>0</Duration>
    <DespawnTime>0</DespawnTime>
    <ProximityRange>-1</ProximityRange>
    <ProximityTriggerSound>500</ProximityTriggerSound>
    <TriggerProbability>1</TriggerProbability>
    <InContainer>False</InContainer>
    <MinRefractory>0</MinRefractory>
    <MaxRefractory>0</MaxRefractory>
    <TODStart>0</TODStart>
    <TODEnd>0</TODEnd>
    <TODMode>0</TODMode>
    <KillReset>1</KillReset>
    <ExternalTriggering>False</ExternalTriggering>
    <SequentialSpawning>-1</SequentialSpawning>
    <AllowGhostTriggering>False</AllowGhostTriggering>
    <SpawnOnTrigger>False</SpawnOnTrigger>
    <SmartSpawning>False</SmartSpawning>
    <Amount>1</Amount>
    <Objects2>Drake:MX=3:SB=0:RT=0:TO=0:KL=0:RK=0:CA=1:DN=-1:DX=-1:SP=1:OBJ=GiantSerpent:MX=4:SB=0:RT=0:TO=0:KL=0:RK=0:CA=1:DN=-1:DX=-1:SP=1:OBJ=Troll:MX=6:SB=0:RT=0:TO=0:KL=0:RK=0:CA=1:DN=-1:DX=-1:SP=1:OBJ=StoneGargoyle:MX=4:SB=0:RT=0:TO=0:KL=0:RK=0:CA=1:DN=-1:DX=-1:SP=1:OBJ=Gargoyle:MX=5:SB=0:RT=0:TO=0:KL=0:RK=0:CA=1:DN=-1:DX=-1:SP=1:OBJ=Mongbat:MX=6:SB=0:RT=0:TO=0:KL=0:RK=0:CA=1:DN=-1:DX=-1:SP=1:OBJ=Ratman:MX=6:SB=0:RT=0:TO=0:KL=0:RK=0:CA=1:DN=-1:DX=-1:SP=1:OBJ=Spectre:MX=4:SB=0:RT=0:TO=0:KL=0:RK=0:CA=1:DN=-1:DX=-1:SP=1</Objects2>
  </Points>
  <Points>
    <Name>Grassland 14</Name>
    <UniqueId>3091caf4-ce34-458e-983a-5112c374ec24</UniqueId>
    <Map>Tykari</Map>
    <X>1344</X>
    <Y>1908</Y>
    <Width>196</Width>
    <Height>480</Height>
    <CentreX>1442</CentreX>
    <CentreY>2148</CentreY>
    <CentreZ>-32768</CentreZ>
    <Range>10</Range>
    <MaxCount>20</MaxCount>
    <MinDelay>300</MinDelay>
    <MaxDelay>600</MaxDelay>
    <Team>0</Team>
    <IsGroup>False</IsGroup>
    <IsRunning>True</IsRunning>
    <IsHomeRangeRelative>True</IsHomeRangeRelative>
    <DelayInSec>True</DelayInSec>
    <Duration>0</Duration>
    <DespawnTime>0</DespawnTime>
    <ProximityRange>-1</ProximityRange>
    <ProximityTriggerSound>500</ProximityTriggerSound>
    <TriggerProbability>1</TriggerProbability>
    <InContainer>False</InContainer>
    <MinRefractory>0</MinRefractory>
    <MaxRefractory>0</MaxRefractory>
    <TODStart>0</TODStart>
    <TODEnd>0</TODEnd>
    <TODMode>0</TODMode>
    <KillReset>1</KillReset>
    <ExternalTriggering>False</ExternalTriggering>
    <SequentialSpawning>-1</SequentialSpawning>
    <AllowGhostTriggering>False</AllowGhostTriggering>
    <SpawnOnTrigger>False</SpawnOnTrigger>
    <SmartSpawning>False</SmartSpawning>
    <Amount>1</Amount>
    <Objects2>Troll:MX=6:SB=0:RT=0:TO=0:KL=0:RK=0:CA=1:DN=-1:DX=-1:SP=1:OBJ=Ogre:MX=4:SB=0:RT=0:TO=0:KL=0:RK=0:CA=1:DN=-1:DX=-1:SP=1:OBJ=OgreLord:MX=1:SB=0:RT=0:TO=0:KL=0:RK=0:CA=1:DN=-1:DX=-1:SP=1:OBJ=StoneGargoyle:MX=2:SB=0:RT=0:TO=0:KL=0:RK=0:CA=1:DN=-1:DX=-1:SP=1:OBJ=StoneHarpy:MX=3:SB=0:RT=0:TO=0:KL=0:RK=0:CA=1:DN=-1:DX=-1:SP=1:OBJ=Cyclops:MX=4:SB=0:RT=0:TO=0:KL=0:RK=0:CA=1:DN=-1:DX=-1:SP=1</Objects2>
  </Points>
  <Points>
    <Name>Grassland 15</Name>
    <UniqueId>8ea63076-ec89-407a-bf18-1fbbb909f6c3</UniqueId>
    <Map>Tykari</Map>
    <X>1556</X>
    <Y>1780</Y>
    <Width>588</Width>
    <Height>296</Height>
    <CentreX>1850</CentreX>
    <CentreY>1928</CentreY>
    <CentreZ>-32768</CentreZ>
    <Range>50</Range>
    <MaxCount>63</MaxCount>
    <MinDelay>300</MinDelay>
    <MaxDelay>720</MaxDelay>
    <Team>0</Team>
    <IsGroup>False</IsGroup>
    <IsRunning>True</IsRunning>
    <IsHomeRangeRelative>True</IsHomeRangeRelative>
    <DelayInSec>True</DelayInSec>
    <Duration>0</Duration>
    <DespawnTime>0</DespawnTime>
    <ProximityRange>-1</ProximityRange>
    <ProximityTriggerSound>500</ProximityTriggerSound>
    <TriggerProbability>1</TriggerProbability>
    <InContainer>False</InContainer>
    <MinRefractory>0</MinRefractory>
    <MaxRefractory>0</MaxRefractory>
    <TODStart>0</TODStart>
    <TODEnd>0</TODEnd>
    <TODMode>0</TODMode>
    <KillReset>1</KillReset>
    <ExternalTriggering>False</ExternalTriggering>
    <SequentialSpawning>-1</SequentialSpawning>
    <AllowGhostTriggering>False</AllowGhostTriggering>
    <SpawnOnTrigger>False</SpawnOnTrigger>
    <SmartSpawning>False</SmartSpawning>
    <Amount>1</Amount>
    <Objects2>Troll:MX=8:SB=0:RT=0:TO=0:KL=0:RK=0:CA=1:DN=-1:DX=-1:SP=1:OBJ=Ratman:MX=12:SB=0:RT=0:TO=0:KL=0:RK=0:CA=1:DN=-1:DX=-1:SP=1:OBJ=RatmanArcher:MX=8:SB=0:RT=0:TO=0:KL=0:RK=0:CA=1:DN=-1:DX=-1:SP=1:OBJ=Orc:MX=10:SB=0:RT=0:TO=0:KL=0:RK=0:CA=1:DN=-1:DX=-1:SP=1:OBJ=OrcishLord:MX=4:SB=0:RT=0:TO=0:KL=0:RK=0:CA=1:DN=-1:DX=-1:SP=1:OBJ=Reaper:MX=3:SB=0:RT=0:TO=0:KL=0:RK=0:CA=1:DN=-1:DX=-1:SP=1:OBJ=Mongbat:MX=8:SB=0:RT=0:TO=0:KL=0:RK=0:CA=1:DN=-1:DX=-1:SP=1:OBJ=HeadlessOne:MX=6:SB=0:RT=0:TO=0:KL=0:RK=0:CA=1:DN=-1:DX=-1:SP=1:OBJ=Gazer:MX=3:SB=0:RT=0:TO=0:KL=0:RK=0:CA=1:DN=-1:DX=-1:SP=1:OBJ=ElderGazer:MX=1:SB=0:RT=0:TO=0:KL=0:RK=0:CA=1:DN=-1:DX=-1:SP=1</Objects2>
  </Points>
  <Points>
    <Name>Grassland 16</Name>
    <UniqueId>d04d845c-d91f-4808-b19c-197904c8a7e7</UniqueId>
    <Map>Tykari</Map>
    <X>2040</X>
    <Y>2088</Y>
    <Width>308</Width>
    <Height>76</Height>
    <CentreX>2194</CentreX>
    <CentreY>2126</CentreY>
    <CentreZ>-32768</CentreZ>
    <Range>50</Range>
    <MaxCount>38</MaxCount>
    <MinDelay>240</MinDelay>
    <MaxDelay>600</MaxDelay>
    <Team>0</Team>
    <IsGroup>False</IsGroup>
    <IsRunning>True</IsRunning>
    <IsHomeRangeRelative>True</IsHomeRangeRelative>
    <DelayInSec>True</DelayInSec>
    <Duration>0</Duration>
    <DespawnTime>0</DespawnTime>
    <ProximityRange>-1</ProximityRange>
    <ProximityTriggerSound>500</ProximityTriggerSound>
    <TriggerProbability>1</TriggerProbability>
    <InContainer>False</InContainer>
    <MinRefractory>0</MinRefractory>
    <MaxRefractory>0</MaxRefractory>
    <TODStart>0</TODStart>
    <TODEnd>0</TODEnd>
    <TODMode>0</TODMode>
    <KillReset>1</KillReset>
    <ExternalTriggering>False</ExternalTriggering>
    <SequentialSpawning>-1</SequentialSpawning>
    <AllowGhostTriggering>False</AllowGhostTriggering>
    <SpawnOnTrigger>False</SpawnOnTrigger>
    <SmartSpawning>False</SmartSpawning>
    <Amount>1</Amount>
    <Objects2>Ettin:MX=4:SB=0:RT=0:TO=0:KL=0:RK=0:CA=1:DN=-1:DX=-1:SP=1:OBJ=Ogre:MX=6:SB=0:RT=0:TO=0:KL=0:RK=0:CA=1:DN=-1:DX=-1:SP=1:OBJ=Troll:MX=6:SB=0:RT=0:TO=0:KL=0:RK=0:CA=1:DN=-1:DX=-1:SP=1:OBJ=Cyclops:MX=3:SB=0:RT=0:TO=0:KL=0:RK=0:CA=1:DN=-1:DX=-1:SP=1:OBJ=Titan:MX=1:SB=0:RT=0:TO=0:KL=0:RK=0:CA=1:DN=-1:DX=-1:SP=1:OBJ=Mongbat:MX=8:SB=0:RT=0:TO=0:KL=0:RK=0:CA=1:DN=-1:DX=-1:SP=1:OBJ=Ratman:MX=6:SB=0:RT=0:TO=0:KL=0:RK=0:CA=1:DN=-1:DX=-1:SP=1:OBJ=OrcCaptain:MX=4:SB=0:RT=0:TO=0:KL=0:RK=0:CA=1:DN=-1:DX=-1:SP=1</Objects2>
  </Points>
  <Points>
    <Name>Grassland 17</Name>
    <UniqueId>97ba4f17-3f48-4585-a58b-2e98e37bd7de</UniqueId>
    <Map>Tykari</Map>
    <X>1697</X>
    <Y>2093</Y>
    <Width>160</Width>
    <Height>96</Height>
    <CentreX>1777</CentreX>
    <CentreY>2141</CentreY>
    <CentreZ>-32768</CentreZ>
    <Range>25</Range>
    <MaxCount>28</MaxCount>
    <MinDelay>300</MinDelay>
    <MaxDelay>720</MaxDelay>
    <Team>0</Team>
    <IsGroup>False</IsGroup>
    <IsRunning>True</IsRunning>
    <IsHomeRangeRelative>True</IsHomeRangeRelative>
    <DelayInSec>True</DelayInSec>
    <Duration>0</Duration>
    <DespawnTime>0</DespawnTime>
    <ProximityRange>-1</ProximityRange>
    <ProximityTriggerSound>500</ProximityTriggerSound>
    <TriggerProbability>1</TriggerProbability>
    <InContainer>False</InContainer>
    <MinRefractory>0</MinRefractory>
    <MaxRefractory>0</MaxRefractory>
    <TODStart>0</TODStart>
    <TODEnd>0</TODEnd>
    <TODMode>0</TODMode>
    <KillReset>1</KillReset>
    <ExternalTriggering>False</ExternalTriggering>
    <SequentialSpawning>-1</SequentialSpawning>
    <AllowGhostTriggering>False</AllowGhostTriggering>
    <SpawnOnTrigger>False</SpawnOnTrigger>
    <SmartSpawning>False</SmartSpawning>
    <Amount>1</Amount>
    <Objects2>Cyclops:MX=3:SB=0:RT=0:TO=0:KL=0:RK=0:CA=1:DN=-1:DX=-1:SP=1:OBJ=Titan:MX=1:SB=0:RT=0:TO=0:KL=0:RK=0:CA=1:DN=-1:DX=-1:SP=1:OBJ=StoneGargoyle:MX=4:SB=0:RT=0:TO=0:KL=0:RK=0:CA=1:DN=-1:DX=-1:SP=1:OBJ=Harpy:MX=4:SB=0:RT=0:TO=0:KL=0:RK=0:CA=1:DN=-1:DX=-1:SP=1:OBJ=StoneHarpy:MX=2:SB=0:RT=0:TO=0:KL=0:RK=0:CA=1:DN=-1:DX=-1:SP=1:OBJ=Mongbat:MX=6:SB=0:RT=0:TO=0:KL=0:RK=0:CA=1:DN=-1:DX=-1:SP=1:OBJ=Bogle:MX=4:SB=0:RT=0:TO=0:KL=0:RK=0:CA=1:DN=-1:DX=-1:SP=1:OBJ=AirElemental:MX=4:SB=0:RT=0:TO=0:KL=0:RK=0:CA=1:DN=-1:DX=-1:SP=1</Objects2>
  </Points>
  <Points>
    <Name>Grassland 18</Name>
    <UniqueId>a057ecba-16fe-4bb3-8523-d23215ee6c90</UniqueId>
    <Map>Tykari</Map>
    <X>2544</X>
    <Y>1628</Y>
    <Width>115</Width>
    <Height>150</Height>
    <CentreX>2601</CentreX>
    <CentreY>1703</CentreY>
    <CentreZ>-32768</CentreZ>
    <Range>25</Range>
    <MaxCount>23</MaxCount>
    <MinDelay>240</MinDelay>
    <MaxDelay>720</MaxDelay>
    <Team>0</Team>
    <IsGroup>False</IsGroup>
    <IsRunning>True</IsRunning>
    <IsHomeRangeRelative>True</IsHomeRangeRelative>
    <DelayInSec>True</DelayInSec>
    <Duration>0</Duration>
    <DespawnTime>0</DespawnTime>
    <ProximityRange>-1</ProximityRange>
    <ProximityTriggerSound>500</ProximityTriggerSound>
    <TriggerProbability>1</TriggerProbability>
    <InContainer>False</InContainer>
    <MinRefractory>0</MinRefractory>
    <MaxRefractory>0</MaxRefractory>
    <TODStart>0</TODStart>
    <TODEnd>0</TODEnd>
    <TODMode>0</TODMode>
    <KillReset>1</KillReset>
    <ExternalTriggering>False</ExternalTriggering>
    <SequentialSpawning>-1</SequentialSpawning>
    <AllowGhostTriggering>False</AllowGhostTriggering>
    <SpawnOnTrigger>False</SpawnOnTrigger>
    <SmartSpawning>False</SmartSpawning>
    <Amount>1</Amount>
    <Objects2>Shade:MX=6:SB=0:RT=0:TO=0:KL=0:RK=0:CA=1:DN=-1:DX=-1:SP=1:OBJ=Troll:MX=3:SB=0:RT=0:TO=0:KL=0:RK=0:CA=1:DN=-1:DX=-1:SP=1:OBJ=Ogre:MX=4:SB=0:RT=0:TO=0:KL=0:RK=0:CA=1:DN=-1:DX=-1:SP=1:OBJ=Reaper:MX=4:SB=0:RT=0:TO=0:KL=0:RK=0:CA=1:DN=-1:DX=-1:SP=1:OBJ=Skeleton:MX=6:SB=0:RT=0:TO=0:KL=0:RK=0:CA=1:DN=-1:DX=-1:SP=1</Objects2>
  </Points>
</Spawns>